{
  "history": [
    {
      "timestamp": "2025-12-15 04:01:00",
      "recordNumber": 1,
      "strongest": [
        {
          "currency": "AUD",
          "w1": 256,
          "d1": 92,
          "avg": 174
        },
        {
          "currency": "EUR",
          "w1": 133,
          "d1": 51,
          "avg": 92
        },
        {
          "currency": "CAD",
          "w1": 24,
          "d1": 134,
          "avg": 79
        }
      ],
      "weakest": [
        {
          "currency": "JPY",
          "w1": -336,
          "d1": -238,
          "avg": -287
        },
        {
          "currency": "USD",
          "w1": -127,
          "d1": -245,
          "avg": -186
        },
        {
          "currency": "GBP",
          "w1": -23,
          "d1": 29,
          "avg": 3
        }
      ],
      "allCurrencies": [
        {
          "currency": "AUD",
          "w1": 256,
          "d1": 92,
          "avg": 174
        },
        {
          "currency": "EUR",
          "w1": 133,
          "d1": 51,
          "avg": 92
        },
        {
          "currency": "CAD",
          "w1": 24,
          "d1": 134,
          "avg": 79
        },
        {
          "currency": "NZD",
          "w1": -50,
          "d1": 204,
          "avg": 77
        },
        {
          "currency": "CHF",
          "w1": 123,
          "d1": -27,
          "avg": 48
        },
        {
          "currency": "GBP",
          "w1": -23,
          "d1": 29,
          "avg": 3
        },
        {
          "currency": "USD",
          "w1": -127,
          "d1": -245,
          "avg": -186
        },
        {
          "currency": "JPY",
          "w1": -336,
          "d1": -238,
          "avg": -287
        }
      ]
    },
    {
      "timestamp": "2025-12-12 20:01:00",
      "recordNumber": 2,
      "strongest": [
        {
          "currency": "AUD",
          "w1": 215,
          "d1": 164,
          "avg": 189.5
        },
        {
          "currency": "EUR",
          "w1": 168,
          "d1": 13,
          "avg": 90.5
        },
        {
          "currency": "CAD",
          "w1": 16,
          "d1": 144,
          "avg": 80
        }
      ],
      "weakest": [
        {
          "currency": "JPY",
          "w1": -353,
          "d1": -298,
          "avg": -325.5
        },
        {
          "currency": "USD",
          "w1": -17,
          "d1": -190,
          "avg": -103.5
        },
        {
          "currency": "GBP",
          "w1": 3,
          "d1": 6,
          "avg": 4.5
        }
      ],
      "allCurrencies": [
        {
          "currency": "AUD",
          "w1": 215,
          "d1": 164,
          "avg": 189.5
        },
        {
          "currency": "EUR",
          "w1": 168,
          "d1": 13,
          "avg": 90.5
        },
        {
          "currency": "CAD",
          "w1": 16,
          "d1": 144,
          "avg": 80
        },
        {
          "currency": "CHF",
          "w1": 130,
          "d1": -34,
          "avg": 48
        },
        {
          "currency": "NZD",
          "w1": -162,
          "d1": 195,
          "avg": 16.5
        },
        {
          "currency": "GBP",
          "w1": 3,
          "d1": 6,
          "avg": 4.5
        },
        {
          "currency": "USD",
          "w1": -17,
          "d1": -190,
          "avg": -103.5
        },
        {
          "currency": "JPY",
          "w1": -353,
          "d1": -298,
          "avg": -325.5
        }
      ]
    },
    {
      "timestamp": "2025-12-12 16:01:00",
      "recordNumber": 3,
      "strongest": [
        {
          "currency": "AUD",
          "w1": 221,
          "d1": 204,
          "avg": 212.5
        },
        {
          "currency": "CAD",
          "w1": 28,
          "d1": 149,
          "avg": 88.5
        },
        {
          "currency": "EUR",
          "w1": 156,
          "d1": -37,
          "avg": 59.5
        }
      ],
      "weakest": [
        {
          "currency": "JPY",
          "w1": -353,
          "d1": -298,
          "avg": -325.5
        },
        {
          "currency": "USD",
          "w1": -29,
          "d1": -185,
          "avg": -107
        },
        {
          "currency": "GBP",
          "w1": -3,
          "d1": 11,
          "avg": 4
        }
      ],
      "allCurrencies": [
        {
          "currency": "AUD",
          "w1": 221,
          "d1": 204,
          "avg": 212.5
        },
        {
          "currency": "CAD",
          "w1": 28,
          "d1": 149,
          "avg": 88.5
        },
        {
          "currency": "EUR",
          "w1": 156,
          "d1": -37,
          "avg": 59.5
        },
        {
          "currency": "NZD",
          "w1": -138,
          "d1": 210,
          "avg": 36
        },
        {
          "currency": "CHF",
          "w1": 118,
          "d1": -54,
          "avg": 32
        },
        {
          "currency": "GBP",
          "w1": -3,
          "d1": 11,
          "avg": 4
        },
        {
          "currency": "USD",
          "w1": -29,
          "d1": -185,
          "avg": -107
        },
        {
          "currency": "JPY",
          "w1": -353,
          "d1": -298,
          "avg": -325.5
        }
      ]
    },
    {
      "timestamp": "2025-12-12 12:01:00",
      "recordNumber": 4,
      "strongest": [
        {
          "currency": "AUD",
          "w1": 227,
          "d1": 199,
          "avg": 213
        },
        {
          "currency": "CAD",
          "w1": 22,
          "d1": 139,
          "avg": 80.5
        },
        {
          "currency": "EUR",
          "w1": 156,
          "d1": -42,
          "avg": 57
        }
      ],
      "weakest": [
        {
          "currency": "JPY",
          "w1": -353,
          "d1": -298,
          "avg": -325.5
        },
        {
          "currency": "USD",
          "w1": -29,
          "d1": -190,
          "avg": -109.5
        },
        {
          "currency": "GBP",
          "w1": -15,
          "d1": 11,
          "avg": -2
        }
      ],
      "allCurrencies": [
        {
          "currency": "AUD",
          "w1": 227,
          "d1": 199,
          "avg": 213
        },
        {
          "currency": "CAD",
          "w1": 22,
          "d1": 139,
          "avg": 80.5
        },
        {
          "currency": "EUR",
          "w1": 156,
          "d1": -42,
          "avg": 57
        },
        {
          "currency": "CHF",
          "w1": 130,
          "d1": -34,
          "avg": 48
        },
        {
          "currency": "NZD",
          "w1": -138,
          "d1": 215,
          "avg": 38.5
        },
        {
          "currency": "GBP",
          "w1": -15,
          "d1": 11,
          "avg": -2
        },
        {
          "currency": "USD",
          "w1": -29,
          "d1": -190,
          "avg": -109.5
        },
        {
          "currency": "JPY",
          "w1": -353,
          "d1": -298,
          "avg": -325.5
        }
      ]
    },
    {
      "timestamp": "2025-12-12 08:01:00",
      "recordNumber": 5,
      "strongest": [
        {
          "currency": "AUD",
          "w1": 221,
          "d1": 204,
          "avg": 212.5
        },
        {
          "currency": "EUR",
          "w1": 158,
          "d1": -32,
          "avg": 63
        },
        {
          "currency": "CAD",
          "w1": -10,
          "d1": 109,
          "avg": 49.5
        }
      ],
      "weakest": [
        {
          "currency": "JPY",
          "w1": -353,
          "d1": -298,
          "avg": -325.5
        },
        {
          "currency": "USD",
          "w1": -29,
          "d1": -200,
          "avg": -114.5
        },
        {
          "currency": "GBP",
          "w1": 45,
          "d1": 16,
          "avg": 30.5
        }
      ],
      "allCurrencies": [
        {
          "currency": "AUD",
          "w1": 221,
          "d1": 204,
          "avg": 212.5
        },
        {
          "currency": "EUR",
          "w1": 158,
          "d1": -32,
          "avg": 63
        },
        {
          "currency": "CAD",
          "w1": -10,
          "d1": 109,
          "avg": 49.5
        },
        {
          "currency": "CHF",
          "w1": 118,
          "d1": -24,
          "avg": 47
        },
        {
          "currency": "NZD",
          "w1": -150,
          "d1": 225,
          "avg": 37.5
        },
        {
          "currency": "GBP",
          "w1": 45,
          "d1": 16,
          "avg": 30.5
        },
        {
          "currency": "USD",
          "w1": -29,
          "d1": -200,
          "avg": -114.5
        },
        {
          "currency": "JPY",
          "w1": -353,
          "d1": -298,
          "avg": -325.5
        }
      ]
    },
    {
      "timestamp": "2025-12-12 04:01:00",
      "recordNumber": 6,
      "strongest": [
        {
          "currency": "AUD",
          "w1": 221,
          "d1": 204,
          "avg": 212.5
        },
        {
          "currency": "EUR",
          "w1": 158,
          "d1": -42,
          "avg": 58
        },
        {
          "currency": "CAD",
          "w1": -10,
          "d1": 109,
          "avg": 49.5
        }
      ],
      "weakest": [
        {
          "currency": "JPY",
          "w1": -353,
          "d1": -298,
          "avg": -325.5
        },
        {
          "currency": "USD",
          "w1": -29,
          "d1": -190,
          "avg": -109.5
        },
        {
          "currency": "GBP",
          "w1": 45,
          "d1": 16,
          "avg": 30.5
        }
      ],
      "allCurrencies": [
        {
          "currency": "AUD",
          "w1": 221,
          "d1": 204,
          "avg": 212.5
        },
        {
          "currency": "EUR",
          "w1": 158,
          "d1": -42,
          "avg": 58
        },
        {
          "currency": "CAD",
          "w1": -10,
          "d1": 109,
          "avg": 49.5
        },
        {
          "currency": "CHF",
          "w1": 118,
          "d1": -24,
          "avg": 47
        },
        {
          "currency": "NZD",
          "w1": -150,
          "d1": 225,
          "avg": 37.5
        },
        {
          "currency": "GBP",
          "w1": 45,
          "d1": 16,
          "avg": 30.5
        },
        {
          "currency": "USD",
          "w1": -29,
          "d1": -190,
          "avg": -109.5
        },
        {
          "currency": "JPY",
          "w1": -353,
          "d1": -298,
          "avg": -325.5
        }
      ]
    },
    {
      "timestamp": "2025-12-11 20:01:00",
      "recordNumber": 7,
      "strongest": [
        {
          "currency": "AUD",
          "w1": 221,
          "d1": 148,
          "avg": 184.5
        },
        {
          "currency": "GBP",
          "w1": 45,
          "d1": 125,
          "avg": 85
        },
        {
          "currency": "EUR",
          "w1": 158,
          "d1": -2,
          "avg": 78
        }
      ],
      "weakest": [
        {
          "currency": "JPY",
          "w1": -347,
          "d1": -278,
          "avg": -312.5
        },
        {
          "currency": "USD",
          "w1": -35,
          "d1": -200,
          "avg": -117.5
        },
        {
          "currency": "CHF",
          "w1": 130,
          "d1": -82,
          "avg": 24
        }
      ],
      "allCurrencies": [
        {
          "currency": "AUD",
          "w1": 221,
          "d1": 148,
          "avg": 184.5
        },
        {
          "currency": "GBP",
          "w1": 45,
          "d1": 125,
          "avg": 85
        },
        {
          "currency": "EUR",
          "w1": 158,
          "d1": -2,
          "avg": 78
        },
        {
          "currency": "CAD",
          "w1": -22,
          "d1": 85,
          "avg": 31.5
        },
        {
          "currency": "NZD",
          "w1": -150,
          "d1": 204,
          "avg": 27
        },
        {
          "currency": "CHF",
          "w1": 130,
          "d1": -82,
          "avg": 24
        },
        {
          "currency": "USD",
          "w1": -35,
          "d1": -200,
          "avg": -117.5
        },
        {
          "currency": "JPY",
          "w1": -347,
          "d1": -278,
          "avg": -312.5
        }
      ]
    }
  ],
  "totalRecords": 7,
  "generatedAt": "2025-12-15T04:00:05.367Z",
  "dataSource": "Google Sheets - FX Cloud Strength",
  "description": "Historical currency strength data - last 7 records"
}